MANIFEST.in
README.rst
requirements.txt
setup.py
pony_traffic.egg-info/PKG-INFO
pony_traffic.egg-info/SOURCES.txt
pony_traffic.egg-info/dependency_links.txt
pony_traffic.egg-info/requires.txt
pony_traffic.egg-info/top_level.txt
request/.middleware.py.swp
request/.models.py.swp
request/.settings.py.swp
request/.traffic.py.swp
request/__init__.py
request/__init__.pyc
request/admin.pyc
request/managers.py
request/managers.pyc
request/middleware.py
request/middleware.pyc
request/models.py
request/models.pyc
request/plugins.py
request/plugins.pyc
request/router.py
request/router.pyc
request/settings.py
request/settings.pyc
request/traffic.py
request/traffic.pyc
request/utils.py
request/utils.pyc
request/admin/.modeladmins.py.swp
request/admin/__init__.py
request/admin/__init__.pyc
request/admin/filters.py
request/admin/filters.pyc
request/admin/modeladmins.py
request/admin/modeladmins.pyc
request/locale/de/LC_MESSAGES/django.mo
request/locale/de/LC_MESSAGES/django.po
request/locale/en/LC_MESSAGES/django.mo
request/locale/en/LC_MESSAGES/django.po
request/locale/es/LC_MESSAGES/django.mo
request/locale/es/LC_MESSAGES/django.po
request/locale/fr/LC_MESSAGES/django.mo
request/locale/fr/LC_MESSAGES/django.po
request/management/__init__.py
request/management/__init__.pyc
request/management/commands/__init__.py
request/management/commands/__init__.pyc
request/management/commands/purgerequests.py
request/management/commands/purgerequests.pyc
request/migrations/0001_initial.py
request/migrations/0001_initial.pyc
request/migrations/0002_alter_request_ip.py
request/migrations/0002_alter_request_ip.pyc
request/migrations/0003_auto_20160331_1430.py
request/migrations/0003_auto_20160331_1430.pyc
request/migrations/0004_alter_time_timezone_default.py
request/migrations/0004_alter_time_timezone_default.pyc
request/migrations/0005_auto_20160511_1545.py
request/migrations/0005_auto_20160511_1545.pyc
request/migrations/__init__.py
request/migrations/__init__.pyc
request/static/request/js/d3.min.js
request/static/request/js/datamaps.world.min.js
request/static/request/js/excanvas.min.js
request/static/request/js/jquery-1.4.2.min.js
