Metadata-Version: 1.1
Name: pony-traffic
Version: 1.0.4
Summary: pony-traffic is a fork of django-request with tracking module. It stores requests in a database for admins to see, it can also be used to get statistics on who is online, where are clients, how much time they spent, etc.
Home-page: http://pony-traffic.readthedocs.org/en/latest/
Author: Anthony Monthe (ZuluPro)
Author-email: anthony.monthe@gmail.com>
License: BSD
Download-URL: http://github.com/ZuluPro/django-request/archive/1.0.4.zip
Platform: UNKNOWN
Classifier: Development Status :: 5 - Production/Stable
Classifier: Environment :: Web Environment
Classifier: Framework :: Django
Classifier: Natural Language :: English
Classifier: Intended Audience :: Developers
Classifier: License :: OSI Approved :: BSD License
Classifier: Operating System :: OS Independent
Classifier: Programming Language :: Python
Classifier: Programming Language :: Python :: 2
Classifier: Programming Language :: Python :: 3
